arduino_communcation/__init__.py
arduino_control-0.0.4.dist-info/METADATA
arduino_control-0.0.4.dist-info/WHEEL
arduino_control-0.0.4.dist-info/top_level.txt
arduino_control-0.0.4.dist-info/RECORD
